nonebot_plugin_qqtophone/__init__.py
nonebot_plugin_qqtophone-0.3.0.dist-info/licenses/LICENSE
nonebot_plugin_qqtophone-0.3.0.dist-info/METADATA
nonebot_plugin_qqtophone-0.3.0.dist-info/WHEEL
nonebot_plugin_qqtophone-0.3.0.dist-info/top_level.txt
nonebot_plugin_qqtophone-0.3.0.dist-info/RECORD
