Metadata-Version: 2.4
Name: nonebot-plugin-qqtophone
Version: 0.3.0
Summary: 基于 Nonebot2，调用 API 获取对应 QQ 号码的信息。
Author-email: StillMisty <1772797842@qq.com>
License:                                  Apache License
Project-URL: Homepage, https://github.com/StillMisty/nonebot_plugin_qqtophone
Keywords: nonebot2,nonebot,plugin
Classifier: Programming Language :: Python :: 3
Classifier: Programming Language :: Python :: 3.10
Classifier: Programming Language :: Python :: 3.11
Classifier: Programming Language :: Python :: 3.12
Classifier: Programming Language :: Python :: 3.13
Classifier: License :: OSI Approved :: Apache Software License
Classifier: Operating System :: OS Independent
Classifier: Topic :: Communications :: Chat
Requires-Python: >=3.10
License-File: LICENSE
Requires-Dist: httpx>=0.27
Requires-Dist: nonebot-adapter-onebot>=2.3
Requires-Dist: nonebot2>=2.3
Dynamic: license-file
